{
  "objectid": 28283,
  "accessionnum": "1943.8.16192",
  "title": "Weather Vane",
  "displaydate": "c. 1939",
  "medium": "watercolor and graphite on paper",
  "dimensions": "overall: 36 x 50.9 cm (14 3/16 x 20 1/16 in.)",
  "attribution": "Harriette Gale",
  "creditline": "Index of American Design",
  "imagecopyright": null,
  "filepath": "28/9CF09E19-43CF-43C6-82B8-6B94A2194B32.jpg",
  "imgvolumepath": "/iiif/public/objects/2/8/2/8/3/",
  "filename": "28283-primary-0-nativeres.ptif/full/!440,400/0/default.jpg",
  "iiif": "https://media.nga.gov/iiif/public/objects/2/8/2/8/3/28283-primary-0-nativeres.ptif/full/!800,800/0/default.jpg",
  "neighbors": ["1943.8.8819", "1943.8.16132", "1943.8.16128", "1943.8.9079", "1943.8.2466", "1943.8.1877"]
}
