{
  "objectid": 6073,
  "accessionnum": "1943.3.2897",
  "title": "Place du Peyra",
  "displaydate": "1928",
  "medium": "etching",
  "dimensions": null,
  "attribution": "Earl Stetson Crawford",
  "creditline": "Rosenwald Collection",
  "imagecopyright": null,
  "filepath": "19/FEE88BD7-5E58-43EB-8BC0-E8A284F181D7.jpg",
  "imgvolumepath": "/iiif/public/objects/6/0/7/3/",
  "filename": "6073-primary-0-nativeres.ptif/full/!325,370/0/default.jpg",
  "iiif": "https://media.nga.gov/iiif/public/objects/6/0/7/3/6073-primary-0-nativeres.ptif/full/!800,800/0/default.jpg",
  "neighbors": ["2011.139.123", "1995.54.35", "1948.3.58", "1942.6.45", "1991.116.140", "2008.115.3490"]
}
