{
  "objectid": 23478,
  "accessionnum": "1943.8.11383",
  "title": "Pinch Vase",
  "displaydate": "c. 1936",
  "medium": "watercolor, gouache, and pen and ink on paper",
  "dimensions": "overall: 30.5 x 22.9 cm (12 x 9 in.)",
  "attribution": "Ralph Atkinson",
  "creditline": "Index of American Design",
  "imagecopyright": null,
  "filepath": "47/65E9449F-B30A-4898-9BAA-B7704B682F52.jpg",
  "imgvolumepath": "/iiif/public/objects/2/3/4/7/8/",
  "filename": "23478-primary-0-nativeres.ptif/full/!250,250/0/default.jpg",
  "iiif": "https://media.nga.gov/iiif/public/objects/2/3/4/7/8/23478-primary-0-nativeres.ptif/full/!800,800/0/default.jpg",
  "neighbors": ["1943.8.5079", "1943.8.7154", "1943.8.5087", "1943.8.7323", "1943.8.6239", "1943.8.7013"]
}
