{
  "objectid": 23014,
  "accessionnum": "1943.8.10919",
  "title": "Cream Pitcher",
  "displaydate": "c. 1936",
  "medium": "watercolor, graphite, and gouache on paperboard",
  "dimensions": "overall: 29.7 x 23.1 cm (11 11/16 x 9 1/8 in.)",
  "attribution": "John Tarantino",
  "creditline": "Index of American Design",
  "imagecopyright": null,
  "filepath": "01/06269A6E-8EBC-47C5-A962-B08E2B223168.jpg",
  "imgvolumepath": "/iiif/public/objects/2/3/0/1/4/",
  "filename": "23014-primary-0-nativeres.ptif/full/!140,90/0/default.jpg",
  "iiif": "https://media.nga.gov/iiif/public/objects/2/3/0/1/4/23014-primary-0-nativeres.ptif/full/!800,800/0/default.jpg",
  "neighbors": ["1943.8.17813", "1943.8.17805", "1943.8.17669", "1943.8.14349", "1943.8.11052", "1943.8.17158"]
}
