{
  "objectid": 23330,
  "accessionnum": "1943.8.11235",
  "title": "Mirror Support",
  "displaydate": "c. 1936",
  "medium": "watercolor, gouache, and graphite on paperboard",
  "dimensions": "overall: 30.5 x 23 cm (12 x 9 1/16 in.)",
  "attribution": "Gertrude Lemberg",
  "creditline": "Index of American Design",
  "imagecopyright": null,
  "filepath": "19/16D3B376-77FD-438B-9974-65461793E3C9.jpg",
  "imgvolumepath": "/iiif/public/objects/2/3/3/3/0/",
  "filename": "23330-primary-0-nativeres.ptif/full/!740,560/0/default.jpg",
  "iiif": "https://media.nga.gov/iiif/public/objects/2/3/3/3/0/23330-primary-0-nativeres.ptif/full/!800,800/0/default.jpg",
  "neighbors": ["1943.8.5248", "1943.8.12201", "1943.8.7570", "1943.8.3529", "1943.8.3421", "1943.8.14068"]
}
