{
  "objectid": 9695,
  "accessionnum": "1943.3.6900",
  "title": "New York from Brooklyn",
  "displaydate": "1910",
  "medium": "lithograph",
  "dimensions": null,
  "attribution": "Joseph Pennell",
  "creditline": "Rosenwald Collection",
  "imagecopyright": null,
  "filepath": "29/E30DCE5D-657A-4F02-822E-D942E52F18B1.jpg",
  "imgvolumepath": "/iiif/public/objects/9/6/9/5/",
  "filename": "9695-primary-0-nativeres.ptif/full/!140,90/0/default.jpg",
  "iiif": "https://media.nga.gov/iiif/public/objects/9/6/9/5/9695-primary-0-nativeres.ptif/full/!800,800/0/default.jpg",
  "neighbors": ["2003.45.3", "1951.16.155", "1955.12.12", "2003.21.2", "1947.7.150", "1943.3.7188"]
}
