{
  "objectid": 8195,
  "accessionnum": "1943.3.5273",
  "title": "Pietà",
  "displaydate": "1903",
  "medium": "lithograph in brown and black on gray-green paper",
  "dimensions": "sheet: 48 x 62.9 cm (18 7/8 x 24 3/4 in.)",
  "attribution": "Käthe Kollwitz",
  "creditline": "Rosenwald Collection",
  "imagecopyright": null,
  "filepath": "12/539FEB65-2537-41C7-8812-7C5CA9F0E020.jpg",
  "imgvolumepath": "/iiif/public/objects/8/1/9/5/",
  "filename": "8195-primary-0-nativeres.ptif/full/!50,50/0/default.jpg",
  "iiif": "https://media.nga.gov/iiif/public/objects/8/1/9/5/8195-primary-0-nativeres.ptif/full/!800,800/0/default.jpg",
  "neighbors": ["2008.115.5186", "1943.4.28", "2006.172.1", "2004.163.5.16", "1957.14.5", "2002.50.55"]
}
