{
  "objectid": 3691,
  "accessionnum": "1943.3.479",
  "title": "Christ on the Cross",
  "displaydate": "c. 1500",
  "medium": "woodcut, hand-colored in blue, green, brown, tan, ocher, olive, pale blue, and gold",
  "dimensions": null,
  "attribution": "German 15th Century",
  "creditline": "Rosenwald Collection",
  "imagecopyright": null,
  "filepath": "08/7432B8F7-11FD-4EB2-AF2A-35102A4D4A63.jpg",
  "imgvolumepath": "/iiif/public/objects/3/6/9/1/",
  "filename": "3691-primary-0-nativeres.ptif/full/!140,90/0/default.jpg",
  "iiif": "https://media.nga.gov/iiif/public/objects/3/6/9/1/3691-primary-0-nativeres.ptif/full/!800,800/0/default.jpg",
  "neighbors": ["1943.3.482", "1980.14.2", "1943.3.661", "1943.3.5777", "2009.60.1", "1996.9.2"]
}
