{
  "objectid": 21486,
  "accessionnum": "1943.8.9390",
  "title": "Chopping Knife",
  "displaydate": "1935/1942",
  "medium": "watercolor, graphite, and gouache on paper",
  "dimensions": "overall: 22.9 x 29.2 cm (9 x 11 1/2 in.)",
  "attribution": "Hester Duany",
  "creditline": "Index of American Design",
  "imagecopyright": null,
  "filepath": "27/A6DAE0DE-4926-4F73-BC5B-6ED57FCBB4F0.jpg",
  "imgvolumepath": "/iiif/public/objects/2/1/4/8/6/",
  "filename": "21486-primary-0-nativeres.ptif/full/!325,370/0/default.jpg",
  "iiif": "https://media.nga.gov/iiif/public/objects/2/1/4/8/6/21486-primary-0-nativeres.ptif/full/!800,800/0/default.jpg",
  "neighbors": ["1943.8.9249", "1943.8.9029", "1943.8.14668", "1943.8.12408", "1943.8.2259", "1943.8.11469"]
}
