{
  "objectid": 8279,
  "accessionnum": "1943.3.5357",
  "title": "Village of Wimille, near Boulogne  (Village de Wimille, pres Boulogne)",
  "displaydate": null,
  "medium": "etching",
  "dimensions": null,
  "attribution": "Alphonse Legros",
  "creditline": "Rosenwald Collection",
  "imagecopyright": null,
  "filepath": "40/FBA7E744-70C6-4525-8D57-D8FECA19A90C.jpg",
  "imgvolumepath": "/iiif/public/objects/8/2/7/9/",
  "filename": "8279-primary-0-nativeres.ptif/full/!740,560/0/default.jpg",
  "iiif": "https://media.nga.gov/iiif/public/objects/8/2/7/9/8279-primary-0-nativeres.ptif/full/!800,800/0/default.jpg",
  "neighbors": ["1952.10.59", "1954.15.2", "1954.15.15", "1951.19.36", "1955.12.5", "1984.1.7"]
}
