{
  "objectid": 29032,
  "accessionnum": "1943.8.16941",
  "title": "Miner's Candlestick",
  "displaydate": "c. 1939",
  "medium": "graphite on paper",
  "dimensions": "overall: 22.5 x 34.2 cm (8 7/8 x 13 7/16 in.)",
  "attribution": "Benjamin Resnick",
  "creditline": "Index of American Design",
  "imagecopyright": null,
  "filepath": "01/EEF87ACD-F28A-4B89-8CE0-8075DD006226.jpg",
  "imgvolumepath": "/iiif/public/objects/2/9/0/3/2/",
  "filename": "29032-primary-0-nativeres.ptif/full/!90,90/0/default.jpg",
  "iiif": "https://media.nga.gov/iiif/public/objects/2/9/0/3/2/29032-primary-0-nativeres.ptif/full/!800,800/0/default.jpg",
  "neighbors": ["1943.8.8254", "1943.8.9003", "1943.8.9394", "1943.8.11937", "1943.8.11415", "1943.8.17048"]
}
