{
  "objectid": 17818,
  "accessionnum": "1943.8.5617",
  "title": "Details of Dining Room Table",
  "displaydate": "c. 1936",
  "medium": "pen and ink and graphite on paperboard",
  "dimensions": "overall: 35.5 x 27.7 cm (14 x 10 7/8 in.)\r\nOriginal IAD Object: none given",
  "attribution": "Howard Weld",
  "creditline": "Index of American Design",
  "imagecopyright": null,
  "filepath": "43/CE64823A-5874-4A67-B99D-E4B329D2B673.jpg",
  "imgvolumepath": "/iiif/public/objects/1/7/8/1/8/",
  "filename": "17818-primary-0-nativeres.ptif/full/!250,250/0/default.jpg",
  "iiif": "https://media.nga.gov/iiif/public/objects/1/7/8/1/8/17818-primary-0-nativeres.ptif/full/!800,800/0/default.jpg",
  "neighbors": ["1943.8.2966", "1943.8.1192", "1943.8.1194", "1980.45.1704", "2001.142.19", "1943.8.1184"]
}
