{
  "objectid": 29436,
  "accessionnum": "1943.8.17345",
  "title": "Sugar Bowl",
  "displaydate": "c. 1940",
  "medium": "watercolor and graphite on paperboard",
  "dimensions": "overall: 28.1 x 22.8 cm (11 1/16 x 9 in.)",
  "attribution": "Rolland Livingstone",
  "creditline": "Index of American Design",
  "imagecopyright": null,
  "filepath": "01/9B42C395-06F6-4A02-92A3-7A0596FBE1F9.jpg",
  "imgvolumepath": "/iiif/public/objects/2/9/4/3/6/",
  "filename": "29436-primary-0-nativeres.ptif/full/!325,370/0/default.jpg",
  "iiif": "https://media.nga.gov/iiif/public/objects/2/9/4/3/6/29436-primary-0-nativeres.ptif/full/!800,800/0/default.jpg",
  "neighbors": ["1943.8.17373", "1943.8.17826", "1943.8.10645", "1943.8.10632", "1943.8.10539", "1943.8.17806"]
}
