{
  "objectid": 25333,
  "accessionnum": "1943.8.13242",
  "title": "Photograph Album",
  "displaydate": "c. 1936",
  "medium": "watercolor and graphite on paper",
  "dimensions": "Original IAD Object: 3 1/2\" high; 10 1/2\" wide; 12 1/4\" long",
  "attribution": "Manuel G. Runyan",
  "creditline": "Index of American Design",
  "imagecopyright": null,
  "filepath": "21/6D650E8C-97DE-46D5-A08A-4AF6C10393CB.jpg",
  "imgvolumepath": "/iiif/public/objects/2/5/3/3/3/",
  "filename": "25333-primary-0-nativeres.ptif/full/!90,90/0/default.jpg",
  "iiif": "https://media.nga.gov/iiif/public/objects/2/5/3/3/3/25333-primary-0-nativeres.ptif/full/!800,800/0/default.jpg",
  "neighbors": ["1943.8.8876", "1943.8.3606", "1943.8.8848", "1943.8.8874", "1943.8.16499", "1943.8.3684"]
}
