{
  "objectid": 33366,
  "accessionnum": "1946.21.108",
  "title": "The Engraver Joseph Tourny (Le graveur Joseph Tourny)",
  "displaydate": "1857",
  "medium": "etching",
  "dimensions": null,
  "attribution": "Edgar Degas",
  "creditline": "Rosenwald Collection",
  "imagecopyright": null,
  "filepath": "40/437AC1A0-413E-4976-9AB2-A84EDC14BF67.jpg",
  "imgvolumepath": "/iiif/public/objects/3/3/3/6/6/",
  "filename": "33366-primary-0-nativeres.ptif/full/!90,90/0/default.jpg",
  "iiif": "https://media.nga.gov/iiif/public/objects/3/3/3/6/6/33366-primary-0-nativeres.ptif/full/!800,800/0/default.jpg",
  "neighbors": ["1943.3.8251", "1995.47.50", "1943.3.8616", "1943.3.8249", "1943.3.7200", "1950.4.18"]
}
