{
  "objectid": 45796,
  "accessionnum": "1958.8.151",
  "title": "A Bishop",
  "displaydate": "c. 1480/1490",
  "medium": "engraving",
  "dimensions": null,
  "attribution": "Martin Schongauer",
  "creditline": "Rosenwald Collection",
  "imagecopyright": null,
  "filepath": "05/B57A7685-884A-445A-9798-386D0DBED63D.jpg",
  "imgvolumepath": "/iiif/public/objects/4/5/7/9/6/",
  "filename": "45796-primary-0-nativeres.ptif/full/!250,250/0/default.jpg",
  "iiif": "https://media.nga.gov/iiif/public/objects/4/5/7/9/6/45796-primary-0-nativeres.ptif/full/!800,800/0/default.jpg",
  "neighbors": ["1943.3.56", "1943.3.914", "1943.3.66", "1946.10.1", "1949.5.304", "1943.3.6243"]
}
