{
  "objectid": 49383,
  "accessionnum": "1964.8.2057",
  "title": "The Land",
  "displaydate": "1960",
  "medium": "lithograph in ten colors on Rives BFK paper",
  "dimensions": null,
  "attribution": "Garo Zareh Antreasian",
  "creditline": "Rosenwald Collection",
  "imagecopyright": null,
  "filepath": "12/3688CF5B-A595-4925-AAE9-90612B541B43.jpg",
  "imgvolumepath": "/iiif/public/objects/4/9/3/8/3/",
  "filename": "49383-primary-0-nativeres.ptif/full/!325,370/0/default.jpg",
  "iiif": "https://media.nga.gov/iiif/public/objects/4/9/3/8/3/49383-primary-0-nativeres.ptif/full/!800,800/0/default.jpg",
  "neighbors": ["1964.8.2058", "1972.34.3", "1964.8.2306", "1943.8.1652", "1943.8.2972", "1943.8.4631"]
}
