{
  "objectid": 48309,
  "accessionnum": "1964.8.1158",
  "title": "Self-Portrait",
  "displaydate": "1956",
  "medium": "lithograph in green, blue, and orange",
  "dimensions": null,
  "attribution": "Oskar Kokoschka",
  "creditline": "Rosenwald Collection",
  "imagecopyright": null,
  "filepath": "08/DB5A8034-D62B-427B-A288-FCB630079F55.jpg",
  "imgvolumepath": "/iiif/public/objects/4/8/3/0/9/",
  "filename": "48309-primary-0-nativeres.ptif/full/!325,370/0/default.jpg",
  "iiif": "https://media.nga.gov/iiif/public/objects/4/8/3/0/9/48309-primary-0-nativeres.ptif/full/!800,800/0/default.jpg",
  "neighbors": ["1974.47.6", "1974.47.4", "1974.47.2", "1974.47.1", "2000.141.698", "1984.64.57.11"]
}
