{
  "objectid": 51599,
  "accessionnum": "1969.15.444",
  "title": "The Bagpipe Player",
  "displaydate": "c. 1622",
  "medium": "etching and engraving",
  "dimensions": null,
  "attribution": "Jacques Callot",
  "creditline": "R.L. Baumfeld Collection",
  "imagecopyright": null,
  "filepath": "12/7FC00805-A6B1-4E76-B357-C744F2B5B276.jpg",
  "imgvolumepath": "/iiif/public/objects/5/1/5/9/9/",
  "filename": "51599-primary-0-nativeres.ptif/full/!140,90/0/default.jpg",
  "iiif": "https://media.nga.gov/iiif/public/objects/5/1/5/9/9/51599-primary-0-nativeres.ptif/full/!800,800/0/default.jpg",
  "neighbors": ["1949.5.257.b", "1969.15.434", "1949.5.259.b", "1969.15.435", "1943.3.5121", "1943.3.8340"]
}
