{
  "objectid": 53651,
  "accessionnum": "1973.15.55",
  "title": "Large House with a Turret",
  "displaydate": "probably c. 1645/1656",
  "medium": "etching",
  "dimensions": null,
  "attribution": "Allart van Everdingen",
  "creditline": "Ailsa Mellon Bruce Fund",
  "imagecopyright": null,
  "filepath": "21/2BA57239-C7C1-4C4A-BD31-D3E3C6FD9FDF.jpg",
  "imgvolumepath": "/iiif/public/objects/5/3/6/5/1/",
  "filename": "53651-primary-0-nativeres.ptif/full/!90,90/0/default.jpg",
  "iiif": "https://media.nga.gov/iiif/public/objects/5/3/6/5/1/53651-primary-0-nativeres.ptif/full/!800,800/0/default.jpg",
  "neighbors": ["1973.15.110", "1973.32.41", "1975.59.3", "1973.15.101", "2014.117.5", "1973.15.25"]
}
