{
  "objectid": 55951,
  "accessionnum": "1976.56.49",
  "title": "Panama Hat",
  "displaydate": "1972",
  "medium": "etching and aquatint in black",
  "dimensions": null,
  "attribution": "David Hockney",
  "creditline": "Gift of the Woodward Foundation, Washington, D.C.",
  "imagecopyright": null,
  "filepath": "11/20CB555C-4B3C-4700-9D1E-245389BB9962.jpg",
  "imgvolumepath": "/iiif/public/objects/5/5/9/5/1/",
  "filename": "55951-primary-0-nativeres.ptif/full/!250,250/0/default.jpg",
  "iiif": "https://media.nga.gov/iiif/public/objects/5/5/9/5/1/55951-primary-0-nativeres.ptif/full/!800,800/0/default.jpg",
  "neighbors": ["1995.36.42", "2017.121.56", "2002.152.10", "2012.118.82", "2007.4.63", "2016.22.291"]
}
