{
  "objectid": 57796,
  "accessionnum": "1980.45.148",
  "title": "(Vertical forms at left and right with criss-cross diagonal beams at center)",
  "displaydate": "1974",
  "medium": "aquatint and etching",
  "dimensions": null,
  "attribution": "Connie Benham",
  "creditline": "Rosenwald Collection",
  "imagecopyright": null,
  "filepath": "39/AE6DF229-2221-426C-B979-FB9AEC3EAFB7.jpg",
  "imgvolumepath": "/iiif/public/objects/5/7/7/9/6/",
  "filename": "57796-primary-0-nativeres.ptif/full/!140,90/0/default.jpg",
  "iiif": "https://media.nga.gov/iiif/public/objects/5/7/7/9/6/57796-primary-0-nativeres.ptif/full/!800,800/0/default.jpg",
  "neighbors": ["2008.115.3757", "1943.8.14781", "2015.19.100", "1998.19.1", "2008.115.3697", "1943.8.13657"]
}
