{
  "objectid": 58891,
  "accessionnum": "1980.45.1177",
  "title": "Title Page",
  "displaydate": "published 1655",
  "medium": "engraving",
  "dimensions": null,
  "attribution": "British 17th Century",
  "creditline": "Rosenwald Collection",
  "imagecopyright": null,
  "filepath": "12/D6701BF7-58C7-41AF-8E12-CF59CF259A87.jpg",
  "imgvolumepath": "/iiif/public/objects/5/8/8/9/1/",
  "filename": "58891-primary-0-nativeres.ptif/full/!740,560/0/default.jpg",
  "iiif": "https://media.nga.gov/iiif/public/objects/5/8/8/9/1/58891-primary-0-nativeres.ptif/full/!800,800/0/default.jpg",
  "neighbors": ["2016.97.1", "1943.3.4959", "1994.80.2", "1985.61.450", "1981.70.2", "2008.115.4839"]
}
