{
  "objectid": 164616,
  "accessionnum": "1981.69.12.206",
  "title": "Veuë du Colisée du Temple du Soleil, et de l'Arc de Titus a Rome",
  "displaydate": "1640-1660",
  "medium": "etching on laid paper",
  "dimensions": "plate: 13.4 × 22.3 cm (5 1/4 × 8 3/4 in.)\r\nsheet: 21.1 × 33 cm (8 5/16 × 13 in.)",
  "attribution": "Israël Silvestre",
  "creditline": "Gift of Robert H. Thayer",
  "imagecopyright": null,
  "filepath": "17/475F6775-7604-41C9-8D18-EC98D8AE084D.jpg",
  "imgvolumepath": "/iiif/public/objects/1/6/4/6/1/6/",
  "filename": "164616-primary-0-nativeres.ptif/full/!90,90/0/default.jpg",
  "iiif": "https://media.nga.gov/iiif/public/objects/1/6/4/6/1/6/164616-primary-0-nativeres.ptif/full/!800,800/0/default.jpg",
  "neighbors": ["1943.3.4916", "1949.5.146", "1968.5.1", "1969.15.244", "1943.3.4716.ss", "1973.32.26"]
}
