{
  "objectid": 66212,
  "accessionnum": "1985.48.37",
  "title": "Tampa 1",
  "displaydate": "1972",
  "medium": "lithograph in black with varnish on waterproof \"tar\" paper",
  "dimensions": null,
  "attribution": "Robert Rauschenberg",
  "creditline": "Gift of Graphicstudio/University of South Florida and the Artist",
  "imagecopyright": null,
  "filepath": "05/6EF9B5C9-F6AC-4886-B906-CAB7321DAD05.jpg",
  "imgvolumepath": "/iiif/public/objects/6/6/2/1/2/",
  "filename": "66212-primary-0-nativeres.ptif/full/!50,50/0/default.jpg",
  "iiif": "https://media.nga.gov/iiif/public/objects/6/6/2/1/2/66212-primary-0-nativeres.ptif/full/!800,800/0/default.jpg",
  "neighbors": ["2008.115.583", "2008.136.48", "1943.3.1019", "1943.8.10136", "1943.8.16565", "1943.3.7613"]
}
