{
  "objectid": 67980,
  "accessionnum": "1986.54.62",
  "title": "Profile, Rowe, Massachusetts",
  "displaydate": "1918",
  "medium": "watercolor over graphite on wove paper",
  "dimensions": "overall: 42.4 x 36 cm (16 11/16 x 14 3/16 in.)",
  "attribution": "John Marin",
  "creditline": "Gift of John Marin, Jr.",
  "imagecopyright": null,
  "filepath": "19/22379475-5A9E-411C-B7DB-F673ADC73D85.jpg",
  "imgvolumepath": "/iiif/public/objects/6/7/9/8/0/",
  "filename": "67980-primary-0-nativeres.ptif/full/!740,560/0/default.jpg",
  "iiif": "https://media.nga.gov/iiif/public/objects/6/7/9/8/0/67980-primary-0-nativeres.ptif/full/!800,800/0/default.jpg",
  "neighbors": ["2009.70.143", "1942.9.280", "2016.191.131", "1943.8.16182", "2006.128.3", "2017.19.12"]
}
