{
  "objectid": 68999,
  "accessionnum": "1986.56.414",
  "title": "Seated Figure Reading",
  "displaydate": null,
  "medium": "(drawing)",
  "dimensions": "overall: 21.6 x 30.4 cm (8 1/2 x 11 15/16 in.)",
  "attribution": "Mark Rothko",
  "creditline": "Gift of The Mark Rothko Foundation, Inc.",
  "imagecopyright": "Copyright © 2005 Kate Rothko Prizel and Christopher Rothko",
  "filepath": "04/253C9103-3E1B-4670-B10E-5A70E2436564.jpg",
  "imgvolumepath": "/iiif/public/objects/6/8/9/9/9/",
  "filename": "68999-primary-0-nativeres.ptif/full/!250,250/0/default.jpg",
  "iiif": "https://media.nga.gov/iiif/public/objects/6/8/9/9/9/68999-primary-0-nativeres.ptif/full/!800,800/0/default.jpg",
  "neighbors": ["2000.141.897", "2000.141.315", "1986.56.147", "2000.141.118", "1986.56.276", "1986.56.437"]
}
