{
  "objectid": 71735,
  "accessionnum": "1990.106.13",
  "title": "Chignon",
  "displaydate": "1981",
  "medium": "watercolor and brush and black ink on Fabriano paper",
  "dimensions": "overall: 56.6 x 76.1 cm (22 5/16 x 29 15/16 in.)",
  "attribution": "Red Grooms",
  "creditline": "Gift of Mrs. Robert A. Hauslohner",
  "imagecopyright": null,
  "filepath": "17/1405C9E1-B7AF-41A9-8A91-7177FCCA1316.jpg",
  "imgvolumepath": "/iiif/public/objects/7/1/7/3/5/",
  "filename": "71735-primary-0-nativeres.ptif/full/!250,250/0/default.jpg",
  "iiif": "https://media.nga.gov/iiif/public/objects/7/1/7/3/5/71735-primary-0-nativeres.ptif/full/!800,800/0/default.jpg",
  "neighbors": ["1986.56.569", "2015.19.591", "2016.140.2", "1943.8.16473", "2008.115.1796", "1943.3.3862"]
}
