{
  "objectid": 74562,
  "accessionnum": "1991.241.24.b",
  "title": "Basket, Table, Door, Window, Mirror, Rug [verso]",
  "displaydate": "1974",
  "medium": "pen and black ink over graphite on wove paper",
  "dimensions": "overall: 22.6 × 32.3 cm (8 7/8 × 12 11/16 in.)\r\nsheet: 19.9 × 29.5 cm (7 13/16 × 11 5/8 in.)",
  "attribution": "Richard Artschwager",
  "creditline": "The Dorothy and Herbert Vogel Collection, Ailsa Mellon Bruce Fund, Patrons' Permanent Fund and Gift of Dorothy and Herbert Vogel",
  "imagecopyright": null,
  "filepath": "33/0EB44189-51AC-4A41-A0DC-9A988989FFD5.jpg",
  "imgvolumepath": "/iiif/public/objects/7/4/5/6/2/",
  "filename": "74562-primary-0-nativeres.ptif/full/!740,560/0/default.jpg",
  "iiif": "https://media.nga.gov/iiif/public/objects/7/4/5/6/2/74562-primary-0-nativeres.ptif/full/!800,800/0/default.jpg",
  "neighbors": ["2001.142.21", "1991.241.25.b", "1971.83.29", "2001.142.20", "1991.241.24.a", "1943.8.1656"]
}
