{
  "objectid": 78638,
  "accessionnum": "1991.208.69",
  "title": "Thomas Campanella",
  "displaydate": "1658",
  "medium": "engraving on laid paper",
  "dimensions": "plate: 15.9 x 11.9 cm (6 1/4 x 4 11/16 in.)\r\nsheet: 28.1 x 20.5 cm (11 1/16 x 8 1/16 in.)",
  "attribution": "Balthasar Moncornet",
  "creditline": "Gift of John O'Brien",
  "imagecopyright": null,
  "filepath": "27/C0337F3B-D86D-4A6C-81B5-4409AFCDEDD3.jpg",
  "imgvolumepath": "/iiif/public/objects/7/8/6/3/8/",
  "filename": "78638-primary-0-nativeres.ptif/full/!90,90/0/default.jpg",
  "iiif": "https://media.nga.gov/iiif/public/objects/7/8/6/3/8/78638-primary-0-nativeres.ptif/full/!800,800/0/default.jpg",
  "neighbors": ["1991.208.75", "1991.208.59", "1991.208.62", "1991.208.74", "1991.164.44", "1991.164.43"]
}
