{
  "objectid": 75468,
  "accessionnum": "1992.75.15",
  "title": "Self-Portrait: Vertical elliptical motion, large",
  "displaydate": "1974",
  "medium": "gelatin silver print",
  "dimensions": "image: 38.1 x 47.8 cm (15 x 18 13/16 in.)\r\nsheet: 40.6 x 50.6 cm (16 x 19 15/16 in.)",
  "attribution": "Blythe Bohnen",
  "creditline": "Gift of Herbert and Paula Molner",
  "imagecopyright": null,
  "filepath": "28/CEB8E283-F735-4A23-9576-B611142A524C.jpg",
  "imgvolumepath": "/iiif/public/objects/7/5/4/6/8/",
  "filename": "75468-primary-0-nativeres.ptif/full/!250,250/0/default.jpg",
  "iiif": "https://media.nga.gov/iiif/public/objects/7/5/4/6/8/75468-primary-0-nativeres.ptif/full/!800,800/0/default.jpg",
  "neighbors": ["1949.3.556", "1992.75.3", "1980.70.23", "2018.59.1", "1949.3.475", "1949.3.351"]
}
