{
  "objectid": 85917,
  "accessionnum": "1994.19.1",
  "title": "Madonna and Child with John the Baptist",
  "displaydate": "1590s",
  "medium": "etching and engraving on laid paper",
  "dimensions": "plate: 16.5 x 27.7 cm (6 1/2 x 10 7/8 in.)\r\nsheet: 16.8 x 28 cm (6 5/8 x 11 in.)",
  "attribution": "Orazio Farinati after Paolo Farinati",
  "creditline": "Ailsa Mellon Bruce Fund",
  "imagecopyright": null,
  "filepath": "02/B86AD584-A093-47DE-BDA6-8DE35F232F4E.jpg",
  "imgvolumepath": "/iiif/public/objects/8/5/9/1/7/",
  "filename": "85917-primary-0-nativeres.ptif/full/!440,400/0/default.jpg",
  "iiif": "https://media.nga.gov/iiif/public/objects/8/5/9/1/7/85917-primary-0-nativeres.ptif/full/!800,800/0/default.jpg",
  "neighbors": ["1980.45.2290", "1972.65.29", "1956.8.3", "1972.65.15", "1946.21.68", "1971.37.32"]
}
