{
  "objectid": 94963,
  "accessionnum": "1998.31.12",
  "title": "Self-Portrait",
  "displaydate": "1977",
  "medium": "graphite on wove paper",
  "dimensions": "overall: 56.2 x 37.8 cm (22 1/8 x 14 7/8 in.)",
  "attribution": "Alex Katz",
  "creditline": "Gift of the Parnassus Foundation",
  "imagecopyright": null,
  "filepath": "11/E8B001D9-D67D-42FF-975D-0E103E4B4418.jpg",
  "imgvolumepath": "/iiif/public/objects/9/4/9/6/3/",
  "filename": "94963-primary-0-nativeres.ptif/full/!90,90/0/default.jpg",
  "iiif": "https://media.nga.gov/iiif/public/objects/9/4/9/6/3/94963-primary-0-nativeres.ptif/full/!800,800/0/default.jpg",
  "neighbors": ["2001.142.11", "1964.8.1393", "2002.157.12", "2011.144.40", "2011.144.44", "2011.144.37"]
}
