{
  "objectid": 78871,
  "accessionnum": "2000.45.3",
  "title": "Goat with a Violin",
  "displaydate": "1922/1923 (printed 1950)",
  "medium": "woodcut in black on oriental paper",
  "dimensions": "block: 20.1 x 28 cm (7 15/16 x 11 in.)\r\nsheet: 33 x 47.8 cm (13 x 18 13/16 in.)",
  "attribution": "Marc Chagall",
  "creditline": "Gift of Mr. and Mrs. Gerhard E. Pinkus",
  "imagecopyright": null,
  "filepath": "22/A08FD8A1-DD8E-4E82-8A56-573EF39E2F79.jpg",
  "imgvolumepath": "/iiif/public/objects/7/8/8/7/1/",
  "filename": "78871-primary-0-nativeres.ptif/full/!250,250/0/default.jpg",
  "iiif": "https://media.nga.gov/iiif/public/objects/7/8/8/7/1/78871-primary-0-nativeres.ptif/full/!800,800/0/default.jpg",
  "neighbors": ["1995.84.1", "1996.56.12", "1980.45.776", "2008.115.1537", "1954.12.45", "2012.92.416"]
}
