{
  "objectid": 122813,
  "accessionnum": "2000.141.976",
  "title": "Untitled [standing female nude leaning on left arm]",
  "displaydate": "1955-1967",
  "medium": "ink and wash on calendered paper",
  "dimensions": "overall: 40.6 x 27.9 cm (16 x 11 in.)",
  "attribution": "Richard Diebenkorn",
  "creditline": "Gift of Phyllis Diebenkorn",
  "imagecopyright": null,
  "filepath": "36/26869579-F11A-44AE-9A54-7DD99A1A7C52.jpg",
  "imgvolumepath": "/iiif/public/objects/1/2/2/8/1/3/",
  "filename": "122813-primary-0-nativeres.ptif/full/!50,50/0/default.jpg",
  "iiif": "https://media.nga.gov/iiif/public/objects/1/2/2/8/1/3/122813-primary-0-nativeres.ptif/full/!800,800/0/default.jpg",
  "neighbors": ["2000.141.1009", "2008.115.379", "1943.3.5241", "2015.19.1099", "2000.141.1134.a", "2000.141.1136"]
}
