{
  "objectid": 122941,
  "accessionnum": "2000.141.1104",
  "title": "Untitled [seated woman in sandals]",
  "displaydate": "1955-1967",
  "medium": "lithographic crayon on wove paper",
  "dimensions": "overall: 43.2 x 31.8 cm (17 x 12 1/2 in.)",
  "attribution": "Richard Diebenkorn",
  "creditline": "Gift of Phyllis Diebenkorn",
  "imagecopyright": null,
  "filepath": "01/BBF201A7-8B1C-4DCF-A27A-0E892E1853B0.jpg",
  "imgvolumepath": "/iiif/public/objects/1/2/2/9/4/1/",
  "filename": "122941-primary-0-nativeres.ptif/full/!440,400/0/default.jpg",
  "iiif": "https://media.nga.gov/iiif/public/objects/1/2/2/9/4/1/122941-primary-0-nativeres.ptif/full/!800,800/0/default.jpg",
  "neighbors": ["2000.141.782", "2000.141.1005", "2000.141.429", "2000.141.889", "2000.141.595", "2000.141.877"]
}
