{
  "objectid": 122014,
  "accessionnum": "2000.141.207",
  "title": "untitled [standing female nude with arms raised]",
  "displaydate": "1955-1967",
  "medium": "pen and ink on calendered paper",
  "dimensions": "overall: 35.2 x 27.9 cm (13 7/8 x 11 in.)",
  "attribution": "Richard Diebenkorn",
  "creditline": "Gift of Phyllis Diebenkorn",
  "imagecopyright": null,
  "filepath": "27/D0CA75E1-BC9F-4F69-B037-0383A49A6BAD.jpg",
  "imgvolumepath": "/iiif/public/objects/1/2/2/0/1/4/",
  "filename": "122014-primary-0-nativeres.ptif/full/!140,90/0/default.jpg",
  "iiif": "https://media.nga.gov/iiif/public/objects/1/2/2/0/1/4/122014-primary-0-nativeres.ptif/full/!800,800/0/default.jpg",
  "neighbors": ["1986.56.183", "2000.141.319", "2000.141.270", "2000.141.911", "2000.141.453", "2000.141.275"]
}
