{
  "objectid": 115766,
  "accessionnum": "2001.67.192",
  "title": "Chicago 56",
  "displaydate": "1960",
  "medium": "gelatin silver print",
  "dimensions": "image: 25.6 x 33.1 cm (10 1/16 x 13 1/16 in.)\r\nsheet: 27.8 x 35.4 cm (10 15/16 x 13 15/16 in.)",
  "attribution": "Aaron Siskind",
  "creditline": "Patrons' Permanent Fund",
  "imagecopyright": null,
  "filepath": "07/8E48C205-1AD6-4526-BB5C-60E56CBFF1D3.jpg",
  "imgvolumepath": "/iiif/public/objects/1/1/5/7/6/6/",
  "filename": "115766-primary-0-nativeres.ptif/full/!440,400/0/default.jpg",
  "iiif": "https://media.nga.gov/iiif/public/objects/1/1/5/7/6/6/115766-primary-0-nativeres.ptif/full/!800,800/0/default.jpg",
  "neighbors": ["1983.18.364", "1983.18.67", "2018.21.26", "2001.67.114", "2001.22.196", "1990.28.130"]
}
