{
  "objectid": 119921,
  "accessionnum": "2002.98.129",
  "title": "Study of an Arab Head",
  "displaydate": "1895",
  "medium": "herkomertype on wove paper",
  "dimensions": "plate: 23.1 x 18.2 cm (9 1/8 x 7 3/16 in.)\r\nsheet: 30.5 x 23.1 cm (12 x 9 1/8 in.)",
  "attribution": "Hubert von Herkomer",
  "creditline": "Gift of Jacob Kainen",
  "imagecopyright": null,
  "filepath": "21/276EB8E4-CC21-49EC-8E92-41B38150E1A7.jpg",
  "imgvolumepath": "/iiif/public/objects/1/1/9/9/2/1/",
  "filename": "119921-primary-0-nativeres.ptif/full/!50,50/0/default.jpg",
  "iiif": "https://media.nga.gov/iiif/public/objects/1/1/9/9/2/1/119921-primary-0-nativeres.ptif/full/!800,800/0/default.jpg",
  "neighbors": ["1958.8.197", "2015.19.1584.2.11", "2008.115.980", "1958.8.196", "1990.95.33", "2004.23.1"]
}
