{
  "objectid": 129711,
  "accessionnum": "2004.28.33",
  "title": "Two Maps I [working proof with crayon additions]",
  "displaydate": "1965",
  "medium": "lithograph in black with hand-additions in lithographic crayon on Rives BFK paper",
  "dimensions": "sheet: 56.5 x 76.5 cm (22 1/4 x 30 1/8 in.)",
  "attribution": "Jasper Johns",
  "creditline": "Patrons' Permanent Fund and Special Friends of the National Gallery of Art",
  "imagecopyright": null,
  "filepath": "33/552C6E46-C107-4371-9771-A0DBBA237A67.jpg",
  "imgvolumepath": "/iiif/public/objects/1/2/9/7/1/1/",
  "filename": "129711-primary-0-nativeres.ptif/full/!325,370/0/default.jpg",
  "iiif": "https://media.nga.gov/iiif/public/objects/1/2/9/7/1/1/129711-primary-0-nativeres.ptif/full/!800,800/0/default.jpg",
  "neighbors": ["2004.28.35", "2004.28.36", "2004.28.34", "2002.98.269", "1996.90.5", "1981.29.1"]
}
