{
  "objectid": 136423,
  "accessionnum": "2006.133.88",
  "title": "Carte photographique de la lune",
  "displaydate": "1904",
  "medium": "photogravure",
  "dimensions": "image: 31.59 x 26.35 cm (12 7/16 x 10 3/8 in.)\r\nplate: 38.58 x 30 cm (15 3/16 x 11 13/16 in.)\r\nsheet: 48.9 x 37.94 cm (19 1/4 x 14 15/16 in.)",
  "attribution": "Charles Le Morvan",
  "creditline": "Gift of Mary and Dan Solomon and Patrons' Permanent Fund",
  "imagecopyright": null,
  "filepath": "18/C513857A-296E-44B7-9D72-5BDB41146A6A.jpg",
  "imgvolumepath": "/iiif/public/objects/1/3/6/4/2/3/",
  "filename": "136423-primary-0-nativeres.ptif/full/!140,90/0/default.jpg",
  "iiif": "https://media.nga.gov/iiif/public/objects/1/3/6/4/2/3/136423-primary-0-nativeres.ptif/full/!800,800/0/default.jpg",
  "neighbors": ["2018.22.1.17", "2018.22.1.12", "2006.133.89", "2018.22.1.41", "2018.22.1.47", "2018.22.1.46"]
}
