{
  "objectid": 137090,
  "accessionnum": "2006.122.135",
  "title": "Starry Night: August",
  "displaydate": "1996",
  "medium": "color soapground aquatint with aquatint on wove Somerset paper",
  "dimensions": "plate: 50.5 x 45.5 cm (19 7/8 x 17 15/16 in.)\r\nsheet: 70.5 x 64.5 cm (27 3/4 x 25 3/8 in.)",
  "attribution": "Pat Steir",
  "creditline": "Gift of Kathan Brown",
  "imagecopyright": null,
  "filepath": "01/6A3D8E41-CE12-4493-BCE7-CF65D71151F6.jpg",
  "imgvolumepath": "/iiif/public/objects/1/3/7/0/9/0/",
  "filename": "137090-primary-0-nativeres.ptif/full/!250,250/0/default.jpg",
  "iiif": "https://media.nga.gov/iiif/public/objects/1/3/7/0/9/0/137090-primary-0-nativeres.ptif/full/!800,800/0/default.jpg",
  "neighbors": ["2006.122.136", "1998.16.1", "1982.21.1", "1943.8.7630", "2010.116.184", "2011.139.171"]
}
