{
  "objectid": 77669,
  "accessionnum": "2007.6.118",
  "title": "Plaster Surrogate",
  "displaydate": "1983",
  "medium": "enamel on cast Hydro-Stone",
  "dimensions": "overall: 17.8 x 10.2 cm (7 x 4 in.)",
  "attribution": "Allan McCollum",
  "creditline": "Dorothy and Herbert Vogel Collection",
  "imagecopyright": null,
  "filepath": "47/E1A91B9B-54D6-465B-830E-F524A611FC84.jpg",
  "imgvolumepath": "/iiif/public/objects/7/7/6/6/9/",
  "filename": "77669-primary-0-nativeres.ptif/full/!740,560/0/default.jpg",
  "iiif": "https://media.nga.gov/iiif/public/objects/7/7/6/6/9/77669-primary-0-nativeres.ptif/full/!800,800/0/default.jpg",
  "neighbors": ["2007.6.119", "2014.136.402", "1943.8.5964", "1943.8.5261", "1943.8.5282", "2014.136.382"]
}
