{
  "objectid": 149383,
  "accessionnum": "2008.115.4693",
  "title": "Copa de Oro",
  "displaydate": "c. 1945",
  "medium": "screenprint",
  "dimensions": "Image: 245 x 347 mm\r\nSheet: 316 x 418 mm",
  "attribution": "Jean Donald Swiggett",
  "creditline": "Reba and Dave Williams Collection, Gift of Reba and Dave Williams",
  "imagecopyright": null,
  "filepath": "16/AF11F47D-D403-4841-B850-E19002C4EC0E.jpg",
  "imgvolumepath": "/iiif/public/objects/1/4/9/3/8/3/",
  "filename": "149383-primary-0-nativeres.ptif/full/!325,370/0/default.jpg",
  "iiif": "https://media.nga.gov/iiif/public/objects/1/4/9/3/8/3/149383-primary-0-nativeres.ptif/full/!800,800/0/default.jpg",
  "neighbors": ["2008.115.2688", "1943.3.7416", "1943.3.8858", "2008.115.2045", "1981.80.24", "1973.65.4"]
}
