{
  "objectid": 147320,
  "accessionnum": "2008.115.2527",
  "title": "Cold Steel",
  "displaydate": "1934",
  "medium": "lithograph in black on wove paper",
  "dimensions": "image: 26.35 × 40.64 cm (10 3/8 × 16 in.)\r\nsheet: 29.21 × 43.34 cm (11 1/2 × 17 1/16 in.)",
  "attribution": "Carl Hoeckner",
  "creditline": "Reba and Dave Williams Collection, Gift of Reba and Dave Williams",
  "imagecopyright": null,
  "filepath": "39/A0451B8F-6BD4-43B0-BBD3-ED972505DE46.jpg",
  "imgvolumepath": "/iiif/public/objects/1/4/7/3/2/0/",
  "filename": "147320-primary-0-nativeres.ptif/full/!740,560/0/default.jpg",
  "iiif": "https://media.nga.gov/iiif/public/objects/1/4/7/3/2/0/147320-primary-0-nativeres.ptif/full/!800,800/0/default.jpg",
  "neighbors": ["2002.157.35", "2015.19.1409", "2008.115.2537", "1973.64.1", "1981.80.21", "1986.3.39"]
}
