{
  "objectid": 144857,
  "accessionnum": "2009.13.4.b",
  "title": "Study for \"Wind from the Sea\" (verso)",
  "displaydate": "c. 1947",
  "medium": "graphite on wove paper",
  "dimensions": "sheet: 37.78 x 55.72 cm (14 7/8 x 21 15/16 in.)",
  "attribution": "Andrew Wyeth",
  "creditline": "Gift of Charles H. Morgan",
  "imagecopyright": "© Andrew Wyeth",
  "filepath": "15/7BEE78DC-3124-40FF-A7DB-B08CD0638BCB.jpg",
  "imgvolumepath": "/iiif/public/objects/1/4/4/8/5/7/",
  "filename": "144857-primary-0-nativeres.ptif/full/!140,90/0/default.jpg",
  "iiif": "https://media.nga.gov/iiif/public/objects/1/4/4/8/5/7/144857-primary-0-nativeres.ptif/full/!800,800/0/default.jpg",
  "neighbors": ["2014.49.1", "1986.56.452", "1999.114.1", "2000.141.199", "1986.56.43", "1995.58.40"]
}
