{
  "objectid": 157385,
  "accessionnum": "2011.144.44",
  "title": "Faces #7",
  "displaydate": "1998",
  "medium": "chromogenic print",
  "dimensions": "image: 45.7 x 36.6 cm (18 x 14 7/16 in.)\r\nsheet: 46.4 x 37.3 cm (18 1/4 x 14 11/16 in.)",
  "attribution": "Vibeke Tandberg",
  "creditline": "Gift of the Heather and Tony Podesta Collection",
  "imagecopyright": null,
  "filepath": "50/7A6C0AE5-04FB-497F-B69E-29E8BAFFBD7C.jpg",
  "imgvolumepath": "/iiif/public/objects/1/5/7/3/8/5/",
  "filename": "157385-primary-0-nativeres.ptif/full/!740,560/0/default.jpg",
  "iiif": "https://media.nga.gov/iiif/public/objects/1/5/7/3/8/5/157385-primary-0-nativeres.ptif/full/!800,800/0/default.jpg",
  "neighbors": ["2011.144.40", "2011.144.35", "2011.144.37", "2011.144.43", "2011.144.42", "2001.147.69"]
}
