{
  "objectid": 163406,
  "accessionnum": "2014.70.2",
  "title": "Smoky Valley (Native American) Village Site Circa 1000-1500 AD, Saline County, Kansas",
  "displaydate": "April 30, 1992",
  "medium": "gelatin silver print, printed 1993",
  "dimensions": "image: 37.9 × 37.8 cm (14 15/16 × 14 7/8 in.)\r\nsheet: 50 × 40.3 cm (19 11/16 × 15 7/8 in.)",
  "attribution": "Terry Evans",
  "creditline": "Robert B. Menschel and the Vital Projects Fund",
  "imagecopyright": null,
  "filepath": "26/D72C65E2-517B-4E4F-B5CA-6A6238077CEA.jpg",
  "imgvolumepath": "/iiif/public/objects/1/6/3/4/0/6/",
  "filename": "163406-primary-0-nativeres.ptif/full/!250,250/0/default.jpg",
  "iiif": "https://media.nga.gov/iiif/public/objects/1/6/3/4/0/6/163406-primary-0-nativeres.ptif/full/!800,800/0/default.jpg",
  "neighbors": ["2015.19.5078.10", "1986.3.52", "1943.3.8096", "2004.72.8", "2004.155.5.4", "2003.86.31"]
}
