{
  "objectid": 164930,
  "accessionnum": "2014.18.20",
  "title": "Looking Out",
  "displaydate": "1875",
  "medium": "graphite and Chinese white on gray wove paper",
  "dimensions": "sheet: 25.08 × 35.24 cm (9 7/8 × 13 7/8 in.)",
  "attribution": "Winslow Homer",
  "creditline": "Collection of Mr. and Mrs. Paul Mellon",
  "imagecopyright": null,
  "filepath": "04/13377CC7-FC42-4BBF-8366-249B0AF79CB7.jpg",
  "imgvolumepath": "/iiif/public/objects/1/6/4/9/3/0/",
  "filename": "164930-primary-0-nativeres.ptif/full/!440,400/0/default.jpg",
  "iiif": "https://media.nga.gov/iiif/public/objects/1/6/4/9/3/0/164930-primary-0-nativeres.ptif/full/!800,800/0/default.jpg",
  "neighbors": ["1975.34.31", "1943.3.1586", "2015.19.454", "1981.4.2", "1978.19.4", "1949.5.125"]
}
