{
  "objectid": 202934,
  "accessionnum": "2015.115.47",
  "title": "Death Ship of No Port",
  "displaydate": "1967",
  "medium": "lithograph in red, black, and yellow on wove paper",
  "dimensions": "sheet: 45.72 × 60.96 cm (18 × 24 in.)",
  "attribution": "H.C. Westermann",
  "creditline": "Gift of Bob Stana and Tom Judy",
  "imagecopyright": null,
  "filepath": "08/3C14AFD5-4525-4C9D-8E91-82E484AE0CB6.jpg",
  "imgvolumepath": "/iiif/public/objects/2/0/2/9/3/4/",
  "filename": "202934-primary-0-nativeres.ptif/full/!325,370/0/default.jpg",
  "iiif": "https://media.nga.gov/iiif/public/objects/2/0/2/9/3/4/202934-primary-0-nativeres.ptif/full/!800,800/0/default.jpg",
  "neighbors": ["1964.8.1322", "1990.88.1", "1980.45.976", "2008.115.3273", "1995.29.25", "1996.120.34"]
}
