{
  "objectid": 216318,
  "accessionnum": "2019.12.14",
  "title": "Captain James Gillette",
  "displaydate": "c. 1864",
  "medium": "albumen print (carte-de-visite)",
  "dimensions": "image/sheet: 9 × 5.5 cm (3 9/16 × 2 3/16 in.)\r\nmount: 10.1 × 6.1 cm (4 × 2 3/8 in.)",
  "attribution": "Johnson Brothers",
  "creditline": "Pepita Milmore Memorial Fund",
  "imagecopyright": null,
  "filepath": "39/49A1E992-A9C8-4AAA-AD35-F6C7A19522EA.jpg",
  "imgvolumepath": "/iiif/public/objects/2/1/6/3/1/8/",
  "filename": "216318-primary-0-nativeres.ptif/full/!50,50/0/default.jpg",
  "iiif": "https://media.nga.gov/iiif/public/objects/2/1/6/3/1/8/216318-primary-0-nativeres.ptif/full/!800,800/0/default.jpg",
  "neighbors": ["1975.10.2", "2015.19.748", "1975.10.15", "1944.5.250", "1942.8.33", "1949.3.576"]
}
